{"items":[{"key":"start_description","value":"%00@ is about to argue with %10@."},{"key":"both gets annoyed_description","value":"%00@ got into an argument with %10@."},{"key":"both gets annoyed_log1","value":"%00@ got into an argument with %10@."},{"key":"character 1 injured_description","value":"%00@ got into an argument with %10@."},{"key":"character 1 injured_log1","value":"%00@ got into an argument with %10@."},{"key":"character 2 injured_description","value":"%00@ got into an argument with %10@."},{"key":"character 2 injured_log1","value":"%00@ got into an argument with %10@."}]}